[
	{
		"name": "menu-0-1",
		"addedAt": "2026-02-16",
		"category": ["Layout", "Navigation, Maps, and POIs"],
		"keywords": ["menu", "navigation", "options", "sidebar", "list"]
	},
	{
		"name": "menu-0-2",
		"addedAt": "2026-02-16",
		"category": ["Layout", "Navigation, Maps, and POIs"],
		"keywords": ["menu", "navigation", "options", "sidebar", "list"]
	},
	{
		"name": "dashboard-0-1",
		"addedAt": "2026-02-16",
		"category": ["Layout"],
		"keywords": ["dashboard", "layout", "grid", "panel", "widgets"]
	},
	{
		"name": "dashboard-0-2",
		"addedAt": "2026-02-16",
		"category": ["Layout"],
		"keywords": ["dashboard", "layout", "grid", "panel", "widgets"]
	},
	{
		"name": "dashboard-0-3",
		"addedAt": "2026-02-16",
		"category": ["Layout"],
		"keywords": ["dashboard", "layout", "grid", "panel", "widgets"]
	},
	{
		"name": "eye",
		"addedAt": "2026-02-16",
		"category": ["Design"],
		"keywords": ["eye", "show", "visible", "view", "watch", "preview", "open"]
	},
	{
		"name": "bookmark",
		"addedAt": "2026-02-16",
		"category": ["File icons"],
		"keywords": ["save", "favorite", "tag", "mark", "clip"]
	},
	{
		"name": "bookmark-check",
		"addedAt": "2026-02-16",
		"category": ["File icons"],
		"keywords": ["saved", "favorite", "done", "added", "clip"]
	},
	{
		"name": "bookmark-minus",
		"addedAt": "2026-02-16",
		"category": ["File icons"],
		"keywords": ["saved", "favorite", "done", "added", "clip"]
	},
	{
		"name": "bookmark-remove",
		"addedAt": "2026-02-16",
		"category": ["File icons"],
		"keywords": ["unsave", "remove", "delete", "unmark", "cancel"]
	},
	{
		"name": "loading-0-1",
		"addedAt": "2026-02-16",
		"category": ["Layout"],
		"keywords": ["loading", "loader", "wait", "busy", "progress", "spinner"]
	},
	{
		"name": "loading-0-2",
		"addedAt": "2026-02-16",
		"category": ["Layout"],
		"keywords": ["loading", "loader", "wait", "busy", "progress", "spinner"]
	},
	{
		"name": "copy",
		"addedAt": "2026-02-16",
		"category": ["Tools"],
		"keywords": ["duplicate", "clone"]
	},
	{
		"name": "download",
		"addedAt": "2026-02-16",
		"category": ["File icons"],
		"keywords": ["export", "file", "save", "fetch", "get"]
	},
	{
		"name": "heart",
		"addedAt": "2026-02-16",
		"category": ["Social", "Emoji"],
		"keywords": ["like", "love", "emotion", "favorite", "react"]
	},
	{
		"name": "search",
		"addedAt": "2026-02-16",
		"category": ["Tools"],
		"keywords": ["find", "magnifier", "search", "explore", "query"]
	},
	{
		"name": "check",
		"addedAt": "2026-02-16",
		"category": ["Notification"],
		"keywords": ["check", "tick", "done", "confirm", "success", "ok"]
	},
	{
		"name": "check-check",
		"addedAt": "2026-02-16",
		"category": ["Notification", "Communication"],
		"keywords": ["check", "double", "done", "all", "success", "confirm"]
	},
	{
		"name": "notification",
		"addedAt": "2026-02-16",
		"category": ["Notification"],
		"keywords": ["notification", "alarm", "alert", "reminder", "ring"]
	},
	{
		"name": "notification-off",
		"addedAt": "2026-02-16",
		"category": ["Notification"],
		"keywords": ["notification", "alarm", "alert", "reminder", "ring"]
	},
	{
		"name": "chevron-right",
		"addedAt": "2026-02-16",
		"category": ["Arrows", "Navigation, Maps, and POIs"],
		"keywords": ["next", "carat", "right", "forward", "continue"]
	},
	{
		"name": "activity",
		"addedAt": "2026-02-16",
		"category": ["Medical"],
		"keywords": ["pulse", "motion", "health", "fitness", "monitor"]
	},
	{
		"name": "compass-0-1",
		"addedAt": "2026-02-16",
		"category": ["Navigation, Maps, and POIs"],
		"keywords": ["direction", "navigation", "explore", "travel", "map"]
	},
	{
		"name": "compass-0-2",
		"addedAt": "2026-02-16",
		"category": ["Navigation, Maps, and POIs"],
		"keywords": ["direction", "navigation", "explore", "travel", "map"]
	},
	{
		"name": "mouse-pointer-click-0-1",
		"addedAt": "2026-02-16",
		"category": ["Cursors"],
		"keywords": ["click", "select"]
	},
	{
		"name": "discord",
		"addedAt": "2026-02-16",
		"category": ["Brands", "Connectivity"],
		"keywords": ["discord", "chat", "community", "gaming", "social"]
	},
	{
		"name": "facebook",
		"addedAt": "2026-02-16",
		"category": ["Brands", "Connectivity"],
		"keywords": ["social", "network", "friends", "meta", "community"]
	},
	{
		"name": "new-twitter",
		"addedAt": "2026-02-16",
		"category": ["Brands", "Connectivity"],
		"keywords": ["social", "tweet", "post", "x", "network"]
	},
	{
		"name": "twitter",
		"addedAt": "2026-02-16",
		"category": ["Brands", "Connectivity"],
		"keywords": ["social", "tweet", "post", "x", "network"]
	},
	{
		"name": "figma",
		"addedAt": "2026-02-16",
		"category": ["Brands"],
		"keywords": ["design", "ui", "tool", "vector", "prototype"]
	},
	{
		"name": "github",
		"addedAt": "2026-02-16",
		"category": ["Brands", "Coding & development"],
		"keywords": ["code", "git", "repo", "version control", "social"]
	},
	{
		"name": "settings-0-1",
		"addedAt": "2026-02-16",
		"category": ["Accounts & access", "Tools"],
		"keywords": ["settings", "configuration", "options", "preferences", "gear"]
	},
	{
		"name": "settings-0-2",
		"addedAt": "2026-02-16",
		"category": ["Accounts & access", "Tools"],
		"keywords": ["settings", "configuration", "options", "preferences", "gear"]
	}
]
